foundationallm_agent_plugins_langchain/__init__.py
foundationallm_agent_plugins_langchain/workflow_plugin_manager.py
foundationallm_agent_plugins_langchain/_metadata/foundationallm_manifest.json
foundationallm_agent_plugins_langchain/workflows/__init__.py
foundationallm_agent_plugins_langchain/workflows/foundationallm_langchain_agent_workflow.py
foundationallm_agent_plugins_langchain/workflows/foundationallm_langchain_lcel_workflow.py
foundationallm_agent_plugins_langchain/workflows/foundationallm_langgraph_react_agent_workflow.py
foundationallm_agent_plugins_langchain-0.9.7.post10.dist-info/METADATA
foundationallm_agent_plugins_langchain-0.9.7.post10.dist-info/WHEEL
foundationallm_agent_plugins_langchain-0.9.7.post10.dist-info/top_level.txt
foundationallm_agent_plugins_langchain-0.9.7.post10.dist-info/RECORD
